uchimata/__init__.py
uchimata/static/widget.js
uchimata-0.4.0.dist-info/METADATA
uchimata-0.4.0.dist-info/WHEEL
uchimata-0.4.0.dist-info/licenses/LICENSE
uchimata-0.4.0.dist-info/RECORD
