Metadata-Version: 2.4
Name: uchimata
Version: 0.4.0
Project-URL: homepage, https://github.com/hms-dbmi/uchimata-py
Author-email: David Kouřil <david.kouril@gmail.com>
License: MIT
License-File: LICENSE
Requires-Python: >=3.8
Requires-Dist: anywidget>=0.9.13
Requires-Dist: bioframe>=0.8.0
Requires-Dist: duckdb>=1.3.2
Requires-Dist: marimo>=0.8.22
Requires-Dist: numpy>=1.24.4
Requires-Dist: pandas>=2.0.3
Requires-Dist: pyarrow>=17.0.0
